lgedv/__init__.py
lgedv/server.py
lgedv/analyzers/__init__.py
lgedv/analyzers/memory_analyzer.py
lgedv/analyzers/race_analyzer.py
lgedv/analyzers/resource_analyzer.py
lgedv/handlers/__init__.py
lgedv/handlers/api_context_handler.py
lgedv/handlers/interface_handler.py
lgedv/handlers/markitdown_handler.py
lgedv/handlers/prompt_handlers.py
lgedv/handlers/requirement_handler.py
lgedv/handlers/resource_handler.py
lgedv/handlers/tool_handlers.py
lgedv/modules/__init__.py
lgedv/modules/config.py
lgedv/modules/data_models.py
lgedv/modules/file_utils.py
lgedv/modules/persistent_storage.py
lgedv/modules/report.py
lgedv/modules/report_leak.py
lgedv/modules/report_race.py
lgedv/modules/report_resource.py
lgedv/modules/report_rule.py
lgedv/modules/resource_analyzer.py
lgedv/modules/rule_fetcher.py
lgedv/prompts/__init__.py
lgedv/prompts/prompt_templates.py
lgedv/resources/AutosarCpp14RuleGuide.md
lgedv/resources/CertcppGuidelines_en.md
lgedv/resources/CriticalRuleGuideLines.md
lgedv/resources/CustomRule.md
lgedv/resources/LGEDVRuleGuide.md
lgedv/resources/MisraC2023RuleGuide.md
lgedv/resources/Misracpp2008Guidelines_en.md
lgedv/resources/StaticAnalysis.md
codeguard_lgedv-1.17.0.dist-info/METADATA
codeguard_lgedv-1.17.0.dist-info/WHEEL
codeguard_lgedv-1.17.0.dist-info/entry_points.txt
codeguard_lgedv-1.17.0.dist-info/RECORD
